{
	"size" : 3,
	"users" : [
		{
			"UserName" : "chizco06",
			"Password" : "10MMP1OPH111H111",
			"Name" : "Francisco Murillo",
			"Age" : "21",
			"Genre" : [
				"Clasica",
				"Heavy Metal",
				"Rock"
			],
			"Friend" : [
				"master"
			],
			"Fsize" : 1,
			"Gsize" : 3,
			"Recomend" : [],
			"Rsize" : 0
		},
		{
			"UserName" : "loop",
			"Password" : "120768095511111111",
			"Name" : "Alejandro Campos",
			"Age" : "21",
			"Genre" : [
				"Rock",
				"Heavy Metal",
				"Rap"
			],
			"Friend" : [
				"chizco06"
			],
			"Fsize" : 1,
			"Gsize" : 3,
			"Recomend" : [],
			"Rsize" : 0
		},
		{
			"UserName" : "master",
			"Password" : "",
			"Name" : "",
			"Age" : "",
			"Genre" : [],
			"Friend" : [],
			"Fsize" : 0,
			"Gsize" : 0,
			"Recomend" : [],
			"Rsize" : 0
		}
	]
}